{
  "chunk_id": "III_i_2_D_38",
  "content": "/>\nIII.i.2.D.4.c\n.\nExample: Situation Requiring Certification of Eligibility and Continued Entitlement\nThe paragraphs below describe\na situation that would require certification of eligibility and continued entitlement, and\nthe appropriate actions to take based on the specific set of facts.\nSituation\n:\nVA receives reliable evidence indicating a surviving spouse in receipt of pension might have remarried.\nThe surviving spouse has no children.\nA review of the claims folder shows the most recent documentation confirming the surviving spouse’s marital status is a\nVA Form 21-686c\ndated November 12, 2004.\nOn February 11, 2010, VA sends notice of proposed adverse action to the surviving spouse\nrequesting completion of\nVA Form 21-686c\n, and\nadvising her that VA may discontinue benefits effective the first of the month following the date on which the evidence of record shows the beneficiary last confirmed her marital status if she does not return the completed form within 60 days.\nResult\n:  If the surviving spouse does not respond within 60 days\nstop the award effective December 1, 2004, and\nsend proper decision notice.",
  "title": "M21-1, Part III, Subpart i, Chapter 2, Section D - Evidence Requested From the Claimant",
  "citation": "Part III, Subpart i, Chapter 2, Section D",
  "source_url": "https://www.knowva.ebenefits.va.gov/system/templates/selfservice/va_ssnew/help/customer/locale/en-US/portal/554400000001018/content/554400000033257/M21-1-Part-III-Subpart-i-Chapter-2-Section-D-Evidence-Requested-From-the-Claimant",
  "updated": "",
  "scraped_at": "2025-06-16T22:35:58.755777",
  "tags": [
    "m21-1"
  ]
}