{
  "chunk_id": "XIV_none_8_None_8",
  "content": "/>\nXIV.8.1.c\n.\nObjectives of the Fugitive Felon Match\nThe objectives of the fugitive felon match are to\nassist law enforcement agencies in the apprehension of fugitives, and\nprevent payment of benefits to or for fugitive felons.",
  "title": "M21-1, Part XIV, Chapter 8 - Fugitive Felon Match",
  "citation": "Part XIV, Chapter 8, Section None",
  "source_url": "https://www.knowva.ebenefits.va.gov/system/templates/selfservice/va_ssnew/help/customer/locale/en-US/portal/554400000001018/content/554400000173306/M21-1-Part-XIV-Chapter-8-Fugitive-Felon-Match",
  "updated": "",
  "scraped_at": "2025-06-16T23:33:17.983814",
  "tags": [
    "m21-1"
  ]
}