{
  "chunk_id": "IX_iii_1_E_9",
  "content": "/>\nIX.iii.1.E.1.\nd\n.\nPension Rates Paid Less Frequently Than Monthly\nCurrent-law pension benefits are normally paid once each month.  However, they are paid less frequently than monthly if the annual rate payable is less than $228.\nThe net award amount for each payee (primary or apportionee) determines if payments are made less frequently than monthly, per\n38 CFR 3.30\n.",
  "title": "M21-1, Part IX, Subpart iii, Chapter 1, Section E - Pension - Basic Rate Determinations",
  "citation": "Part IX, Subpart iii, Chapter 1, Section E",
  "source_url": "https://www.knowva.ebenefits.va.gov/system/templates/selfservice/va_ssnew/help/customer/locale/en-US/portal/554400000001018/content/554400000177520/M21-1-Part-IX-Subpart-iii-Chapter-1-Section-E-Pension-Basic-Rate-Determinations",
  "updated": "",
  "scraped_at": "2025-06-16T23:07:17.413088",
  "tags": [
    "m21-1"
  ]
}