{
  "chunk_id": "IX_iii_1_E_16",
  "content": "/>\nIX.iii.1.E.2.\nb\n.\nCOLA in MAPR\nIf Social Security benefits are increased as the result of an Social Security cost-of-living adjustment (COLA), pension MAPRs are increased by a like percentage at the same time, per\n38 CFR 3.23(a)\n.\nReferences\n:  For more information on\ncurrent and historical MAPRs, see the\npension rate tables\n, and\nadjustment of pension based on a change in income due to a Social Security COLA, see\nVAOPGCPREC 21-1990\n.",
  "title": "M21-1, Part IX, Subpart iii, Chapter 1, Section E - Pension - Basic Rate Determinations",
  "citation": "Part IX, Subpart iii, Chapter 1, Section E",
  "source_url": "https://www.knowva.ebenefits.va.gov/system/templates/selfservice/va_ssnew/help/customer/locale/en-US/portal/554400000001018/content/554400000177520/M21-1-Part-IX-Subpart-iii-Chapter-1-Section-E-Pension-Basic-Rate-Determinations",
  "updated": "",
  "scraped_at": "2025-06-16T23:07:17.413088",
  "tags": [
    "m21-1"
  ]
}