{
  "chunk_id": "IX_iii_1_G_39",
  "content": "/>\nIntroduction\nThis topic contains information on processing UME deductions, including\ngeneral rule on allowing medical expenses\nrequirements for a medical expense deduction claim\ninformation required for\nmileage of privately owned vehicle\nin-home attendant\n, and\nmedical expenses\nallowing medical expenses prospectively\nexample of annual amount vs. calculated estimated actual amount\ndates for allowing medical expenses prospectively\naward action to adjust after UMEs allowed prospectively\nreconsidering a disallowed claim\nnotice to claimant for prospective medical expenses\nadjusting an award for a change in continuing medical expenses\nnonrecurring medical expenses\nexample 1 of nonrecurring medical expenses\nexample 2 of nonrecurring medical expenses\nexample 3 of nonrecurring medical expenses\noverlapping initial year and calendar year periods\ncounting medical expenses from the effective date to the payment date of the award\neffect of a COLA or change in dependency status on a pension rate\nreimbursed medical expenses\n, and\nrenouncement of claimed medical expenses\n.",
  "title": "M21-1, Part IX, Subpart iii, Chapter 1, Section G - Pension - Deductible Medical Expenses",
  "citation": "Part IX, Subpart iii, Chapter 1, Section G",
  "source_url": "https://www.knowva.ebenefits.va.gov/system/templates/selfservice/va_ssnew/help/customer/locale/en-US/portal/554400000001018/content/554400000177522/M21-1-Part-IX-Subpart-iii-Chapter-1-Section-G-Pension-Deductible-Medical-Expenses",
  "updated": "",
  "scraped_at": "2025-06-16T23:07:36.061469",
  "tags": [
    "m21-1"
  ]
}