{
  "chunk_id": "IX_iii_1_K_7",
  "content": "/>\nIX.iii.1.K.1.b\n.\nDefinition: Last Illness\nFor the purposes of the final expense deduction, the term\nlast illness\nmeans the period from the onset of the acute attack causing death to the date of death.  Generally, expenses incurred more than one year prior to date of death should not be considered expenses of last illness.\nIf death resulted from a lingering or prolonged illness instead of an acute attack, the period of last illness is considered to have begun at the time the person became so ill as to require the regular and daily attendance of another person.",
  "title": "M21-1, Part IX, Subpart iii, Chapter 1, Section K - Other Deductible Expenses",
  "citation": "Part IX, Subpart iii, Chapter 1, Section K",
  "source_url": "https://www.knowva.ebenefits.va.gov/system/templates/selfservice/va_ssnew/help/customer/locale/en-US/portal/554400000001018/content/554400000177526/M21-1-Part-IX-Subpart-iii-Chapter-1-Section-K-Other-Deductible-Expenses",
  "updated": "",
  "scraped_at": "2025-06-16T23:08:13.655409",
  "tags": [
    "m21-1"
  ]
}