{
  "chunk_id": "V_ii_3_D_34",
  "content": "/>\nV.ii.3.D.3.f\n.\nExtra-Schedular Consideration in Pension Claims\nIn pension claims, consider the issue of entitlement to an extra-schedular evaluation under\n38 CFR 3.321(b)(2)\nwhenever a Veteran fails to meet the schedular requirements for permanent and total (P&T) disability.  If approval is recommended, forward the rating decision and claims folder to the Veterans Service Center Manager, Pension Management Center Manager, or designee for signature.",
  "title": "M21-1, Part V, Subpart ii, Chapter 3, Section D - Evaluating Disabilities",
  "citation": "Part V, Subpart ii, Chapter 3, Section D",
  "source_url": "https://www.knowva.ebenefits.va.gov/system/templates/selfservice/va_ssnew/help/customer/locale/en-US/portal/554400000001018/content/554400000180489/M21-1-Part-V-Subpart-ii-Chapter-3-Section-D-Evaluating-Disabilities",
  "updated": "",
  "scraped_at": "2025-06-16T22:42:38.373209",
  "tags": [
    "m21-1"
  ]
}