{
  "chunk_id": "V_ii_4_A_13",
  "content": "/>\nV.ii.4.A.1.h\n.\nImpact of PL 112-154, Section 506, on FDC Effective Dates\nIn certain situations, retroactive effective dates were warranted under\nPublic Law (PL) 112-154\n, Section 506, for certain fully developed claims (FDCs), as is discussed in\nM21-1, Part X, Subpart i, 2.B.4\n, and\nthe attachment,\nHistorical_M21-1III_i_3_SecB_2-19-19.docx\n.\nOtherwise, a claim’s inclusion in the FDC Program does not uniquely impact effective date assignment, and the usual effective date rules relevant to the underlying claim type and/or individual adjudicated issue(s) are for application.",
  "title": "M21-1, Part V, Subpart ii, Chapter 4, Section A - Effective Dates",
  "citation": "Part V, Subpart ii, Chapter 4, Section A",
  "source_url": "https://www.knowva.ebenefits.va.gov/system/templates/selfservice/va_ssnew/help/customer/locale/en-US/portal/554400000001018/content/554400000180492/M21-1-Part-V-Subpart-ii-Chapter-4-Section-A-Effective-Dates",
  "updated": "",
  "scraped_at": "2025-06-16T22:42:48.007241",
  "tags": [
    "m21-1"
  ]
}