{
  "chunk_id": "V_iii_12_B_4",
  "content": "/>\nIntroduction\nThis topic contains information about TBI, including\ndefinition of TBI\nTBI events\nexternal force for the purpose of TBI events\nTBI residuals\ndetermining the issues in TBI cases\nservice connection (SC) of TBI residuals\nevaluation of TBI residuals\nmultiple evaluations and pyramiding in TBI cases\nevaluating TBI and comorbid symptoms/conditions\nexample of evaluating TBI with comorbid conditions\nopinion evidence and separate evaluations of TBI and a mental disorder\nadditional TBI signs or symptoms upon reevaluation\nTBI and special monthly compensation (SMC)\ntemporary total evaluations and TBI\ntraining and signature requirements for TBI decisions\napplicability of 38 CFR 3.114(a) in TBI cases\nTBI special issue\n, and\nanoxic brain injury\n.",
  "title": "M21-1, Part V, Subpart iii, Chapter 12, Section B - Traumatic Brain Injury (TBI)",
  "citation": "Part V, Subpart iii, Chapter 12, Section B",
  "source_url": "https://www.knowva.ebenefits.va.gov/system/templates/selfservice/va_ssnew/help/customer/locale/en-US/portal/554400000001018/content/554400000180832/M21-1-Part-V-Subpart-iii-Chapter-12-Section-B-Traumatic-Brain-Injury-TBI",
  "updated": "",
  "scraped_at": "2025-06-16T22:46:12.482450",
  "tags": [
    "m21-1"
  ]
}