{
  "chunk_id": "V_iii_12_B_20",
  "content": "/>\nV.iii.12.B.1.o\n.\nTraining and Signature Requirements for TBI Decisions\nAll decisions that address TBI as an issue, including rating decisions, Statements of the Case, and Supplemental Statements of the Case, must\nonly\nbe worked/reviewed by a Rating Veterans Service Representative or Decision Review Officer who has completed the required TBI training.\nDecisions for TBI require two signatures until a decision maker has demonstrated an accuracy rate of 90 percent or greater based on a review of at least 10 TBI cases.\nReferences\n:  For more information on\nt\nwo-signature requirements in TBI rating decisions, see\nM21-1, Part V, Subpart iv, 1.B.7.d\n, and\ntraining requirements for TBI determinations, see\nM21-3, Part I, A.3.l\n.",
  "title": "M21-1, Part V, Subpart iii, Chapter 12, Section B - Traumatic Brain Injury (TBI)",
  "citation": "Part V, Subpart iii, Chapter 12, Section B",
  "source_url": "https://www.knowva.ebenefits.va.gov/system/templates/selfservice/va_ssnew/help/customer/locale/en-US/portal/554400000001018/content/554400000180832/M21-1-Part-V-Subpart-iii-Chapter-12-Section-B-Traumatic-Brain-Injury-TBI",
  "updated": "",
  "scraped_at": "2025-06-16T22:46:12.482450",
  "tags": [
    "m21-1"
  ]
}