{
  "chunk_id": "V_iv_1_C_21",
  "content": "/>\nV.iv.1.C.3.d\n.\nShowing Evaluations in Ratings That Apply 38 CFR 3.105(e)\nWhen applying the provisions of\n38 CFR 3.105(e)\nin a final compensation reduction rating, the coded conclusion should show the\ncurrent evaluation in effect, and\nfuture reduced evaluation.",
  "title": "M21-1, Part V, Subpart iv, Chapter 1, Section C - Coded Conclusion",
  "citation": "Part V, Subpart iv, Chapter 1, Section C",
  "source_url": "https://www.knowva.ebenefits.va.gov/system/templates/selfservice/va_ssnew/help/customer/locale/en-US/portal/554400000001018/content/554400000180525/M21-1-Part-V-Subpart-iv-Chapter-1-Section-C-Coded-Conclusion",
  "updated": "",
  "scraped_at": "2025-06-16T22:47:08.257771",
  "tags": [
    "m21-1"
  ]
}