{
  "chunk_id": "VI_ii_2_None_12",
  "content": "/>\nVI.ii.2.1.g\n.\nEffect of PL 87-509 on Readjustment Pay\nPL 87-509\n, enacted June 28, 1962, liberalized the former law that required Veterans to make a one-time, irrevocable election between VA compensation and readjustment pay.  The prior election no longer precludes payment of compensation if a Veteran is otherwise eligible.\nOn or after June 28, 1962, if\na claims folder is encountered in which the Veteran’s claim for compensation was previously barred under the former law, compensation may now be awarded, subject to\nrecoupment of the readjustment pay, and\nthe effective dates for liberalizing legislation, as provided in\n38 CFR 3.114(a)\n, and\npotential eligibility for compensation exists based on the former claim, but there is insufficient evidence to make a decision,\nnotify the Veteran of the evidence necessary to establish eligibility in accordance with\n38 CFR 3.159(b)\n, and\ndevelop for the evidence in accordance with\nM21-1, Part III, Subpart i, 2.C\n, and\n38 CFR 3.159(c)\n.",
  "title": "M21-1, Part VI, Subpart ii, Chapter 2 - Recoupment of Separation Benefits",
  "citation": "Part VI, Subpart ii, Chapter 2, Section None",
  "source_url": "https://www.knowva.ebenefits.va.gov/system/templates/selfservice/va_ssnew/help/customer/locale/en-US/portal/554400000001018/content/554400000179478/M21-1-Part-VI-Subpart-ii-Chapter-2-Recoupment-of-Separation-Benefits",
  "updated": "",
  "scraped_at": "2025-06-16T22:48:32.145895",
  "tags": [
    "m21-1"
  ]
}