{
  "chunk_id": "VI_ii_2_None_46",
  "content": "/>\nVI.ii.2.3.g\n.\nWithholding Compensation When the Veteran Did Not Receive Severance Pay for All SC  Disabilities\nIf VA has awarded SC for both severance- and non-severance-pay disabilities, VA may\nnot\nwithhold an amount greater than that to which the Veteran is entitled based on the non-severance-pay disability(ies).  This includes the additional amount of compensation payable for\ndependents (if the non-severance-pay disabilities\nalone\nhave a combined rating of at least 30 percent), and/or\nSMC (if the SMC is based on non-severance-pay disabilities\nalone\n).",
  "title": "M21-1, Part VI, Subpart ii, Chapter 2 - Recoupment of Separation Benefits",
  "citation": "Part VI, Subpart ii, Chapter 2, Section None",
  "source_url": "https://www.knowva.ebenefits.va.gov/system/templates/selfservice/va_ssnew/help/customer/locale/en-US/portal/554400000001018/content/554400000179478/M21-1-Part-VI-Subpart-ii-Chapter-2-Recoupment-of-Separation-Benefits",
  "updated": "",
  "scraped_at": "2025-06-16T22:48:32.145895",
  "tags": [
    "m21-1"
  ]
}