{
  "chunk_id": "VII_i_2_E_10",
  "content": "/>\nVII.i.2.E.1.e\n.\nWhen to Develop for the Surviving Spouse’s New Name\nIf the surviving spouse’s new name is\nnot\navailable, develop for it only if\nthe surviving spouse\nhas custody of the Veteran's child(ren), or\nremains eligible for VA benefits, and/or\nan overpayment is involved.\nReference\n:  For more information on the action to take when a name change is required, see\nM21-1, Part VII, Subpart i, 2.E.1.f\n.",
  "title": "M21-1, Part VII, Subpart i, Chapter 2, Section E - Remarriage of a Surviving Spouse",
  "citation": "Part VII, Subpart i, Chapter 2, Section E",
  "source_url": "https://www.knowva.ebenefits.va.gov/system/templates/selfservice/va_ssnew/help/customer/locale/en-US/portal/554400000001018/content/554400000176622/M21-1-Part-VII-Subpart-i-Chapter-2-Section-E-Remarriage-of-a-Surviving-Spouse",
  "updated": "",
  "scraped_at": "2025-06-16T22:53:02.514678",
  "tags": [
    "m21-1"
  ]
}