{
  "chunk_id": "VII_i_2_E_31",
  "content": "/>\nVII.i.2.E.3.\nd\n.\nRequesting Information in Pension or DIC Cases\nRequest the following information to be submitted within 60 days:\nin pension cases, request an income statement if current income information is not of record, or\nin DIC cases, request a claim on\nVA Form 21P-534EZ,\nApplication for DIC, Survivors Pension, and/or Accrued Benefits\nwhen required under\n38 CFR 3.152(c)\n.\nUse the table below to determine the actions to take based on whether the information is submitted within 60 days or one year.\nIf the information ...\nThen ...\nis\nnot\nsubmitted within 60 days\nsuspend payments the first of the month following the month for which VA last paid the beneficiary.\nis submitted within one year of request\ntake action, if otherwise in order and subject to action as described in\nM21-1, Part VII, Subpart i, 2.E.3\nand\n4\n, to authorize the full rates payable to children.\nNote\n:  When considering pension entitlement for children, the income of their custodian must also be considered.\nReference\n:  For more information on counting the income of a child’s custodian, see\nM21-1, Part IX, Subpart iii, 1.E.4.f\n.",
  "title": "M21-1, Part VII, Subpart i, Chapter 2, Section E - Remarriage of a Surviving Spouse",
  "citation": "Part VII, Subpart i, Chapter 2, Section E",
  "source_url": "https://www.knowva.ebenefits.va.gov/system/templates/selfservice/va_ssnew/help/customer/locale/en-US/portal/554400000001018/content/554400000176622/M21-1-Part-VII-Subpart-i-Chapter-2-Section-E-Remarriage-of-a-Surviving-Spouse",
  "updated": "",
  "scraped_at": "2025-06-16T22:53:02.514678",
  "tags": [
    "m21-1"
  ]
}