{
  "chunk_id": "VIII_iv_4_A_49",
  "content": "/>\nVIII.iv.4.A.5.b\n.\nBasic Criteria for Entitlement to SMC (m)\nThe SMC rate payable under\n38 U.S.C. 1114(m)\nis authorized for the following disabilities\nanatomical L/LOU of both hands\nanatomical L/LOU of both legs at a level, or with complications, preventing natural knee action with prostheses in place\nanatomical L/LOU of one arm and one leg preventing natural elbow and knee action with prostheses in place, due to the level of involvement or with complications\nblindness in both eyes having LPO, or\nblindness in both eyes leaving the Veteran so significantly disabled as to be in need of regular A&A.",
  "title": "M21-1, Part VIII, Subpart iv, Chapter 4, Section A - Special Monthly Compensation (SMC)",
  "citation": "Part VIII, Subpart iv, Chapter 4, Section A",
  "source_url": "https://www.knowva.ebenefits.va.gov/system/templates/selfservice/va_ssnew/help/customer/locale/en-US/portal/554400000001018/content/554400000177480/M21-1-Part-VIII-Subpart-iv-Chapter-4-Section-A-Special-Monthly-Compensation-SMC",
  "updated": "",
  "scraped_at": "2025-06-16T23:02:47.849145",
  "tags": [
    "m21-1"
  ]
}