{
  "chunk_id": "VIII_iv_4_A_68",
  "content": "/>\nVIII.iv.4.A.5.u\n.\nExample:  Rating Decision Involving SMC for Bilateral Blindness With L/LOU of a Lower Extremity Considered Less Than 50-Percent Disabling\nSituation\n:  The Veteran has\nvisual acuity of 5/200 (1.5/60), bilaterally\na below-the-knee amputation of the right foot evaluated as 40-percent disabling, and\nno other compensable disabilities.\nResult\n:  The Veteran is entitled to SMC under\n38 U.S.C. 1114(l)\nbased on the degree of blindness alone.  The Veteran is also entitled to SMC under\n38 U.S.C. 1114(k)\nfor loss of the right foot.  The appropriate level of SMC, therefore, is “l+k.”  Award an additional one-half step of SMC (l½ +k) under the provisions of\n38 CFR 3.350(f)(2)(vii)(C)\n.\nCoded Conclusion\n:\nThe appropriate SMC paragraph code is P B-6.\nThe appropriate SMC coding is 24-24-21-13-0.\nNote\n:  The SMC Calculator will ask whether the Veteran was on active duty after September 11, 2001.  Answering\nYes\nto that question prompts additional questions regarding the Veteran’s ability to ambulate with and without the use of ambulation aides.  Answering\nNo\nto the question of whether the Veteran was on active duty after September 11, 2001, does not prompt any additional questions.  Depending on the answers provided to the additional prompts, the resulting SMC paragraph code and coding may differ from the example provided.",
  "title": "M21-1, Part VIII, Subpart iv, Chapter 4, Section A - Special Monthly Compensation (SMC)",
  "citation": "Part VIII, Subpart iv, Chapter 4, Section A",
  "source_url": "https://www.knowva.ebenefits.va.gov/system/templates/selfservice/va_ssnew/help/customer/locale/en-US/portal/554400000001018/content/554400000177480/M21-1-Part-VIII-Subpart-iv-Chapter-4-Section-A-Special-Monthly-Compensation-SMC",
  "updated": "",
  "scraped_at": "2025-06-16T23:02:47.849145",
  "tags": [
    "m21-1"
  ]
}