{
  "chunk_id": "X_i_2_B_25",
  "content": "/>\nX.i.2.B.3.f\n.\nTelephone Development and FDC Exclusion\nA telephone call to a claimant to clarify information will not require exclusion from the FDC Program if the telephone call can be completed at the time the action is being taken on the claim.  Exclusion\nwould\nbe appropriate when contact with the claimant is unsuccessful and the need for clarification would require the initiation of additional development.\nExample\n:  A claimant submits medical evidence from a physician and attaches a\nVA Form 21-4142\nor\nVA Form 21-4142a\n.  A claims processor calls the claimant to clarify if the claimant wanted VA to develop for additional records.  Provided the claims processor reaches the claimant the same day and the claimant provided a negative response, the claim will\nnot\nbe excluded from the FDC Program.\nImportant\n:  Exclusion would be appropriate if\nthe claimant cannot be reached at the time of the action being taken on the claim, and\nVA then had to send a letter to the claimant to request the necessary information.",
  "title": "M21-1, Part X, Subpart i, Chapter 2, Section B - Processing Fully Developed Claims (FDCs)",
  "citation": "Part X, Subpart i, Chapter 2, Section B",
  "source_url": "https://www.knowva.ebenefits.va.gov/system/templates/selfservice/va_ssnew/help/customer/locale/en-US/portal/554400000001018/content/554400000177941/M21-1-Part-X-Subpart-i-Chapter-2-Section-B-Processing-Fully-Developed-Claims-FDCs",
  "updated": "",
  "scraped_at": "2025-06-16T23:09:09.422499",
  "tags": [
    "m21-1"
  ]
}