{
  "chunk_id": "X_ii_3_D_16",
  "content": "/>\nX.ii.3.D.2.a\n.\nInvalid Disagreements With Proposed Rating Decisions\nA legacy notice of disagreement (NOD) or request for decision review is not valid if filed in response to a\nnotice of proposed adverse action, or\nnotice of proposed incompetency.\nReferences\n:  For more information on\nlegacy NODs, see\nM21-5, Chapter 7, Section B\n, and\nresponding to invalid or premature legacy NODs, see\nM21-5, Chapter 6, Section B, 1.e\n.",
  "title": "M21-1, Part X, Subpart ii, Chapter 3, Section D - Completing Proposed Rating Decisions",
  "citation": "Part X, Subpart ii, Chapter 3, Section D",
  "source_url": "https://www.knowva.ebenefits.va.gov/system/templates/selfservice/va_ssnew/help/customer/locale/en-US/portal/554400000001018/content/554400000177968/M21-1-Part-X-Subpart-ii-Chapter-3-Section-D-Completing-Proposed-Rating-Decisions",
  "updated": "",
  "scraped_at": "2025-06-16T23:13:20.433842",
  "tags": [
    "m21-1"
  ]
}