{
  "chunk_id": "X_ii_6_E_7",
  "content": "/>\nX.ii.6.E.1.b\n.\nMinor Beneficiaries With Multiple Custodial Parents\nIf it appears more than one natural or adoptive parent is the custodian of a minor, refer this information to the hub of jurisdiction.  The hub will advise which parent to pay.\nIf a current\nVA Form 21P-555\nis not of record, request it by preparing\nVA Form 21-592\nand submitting it to the hub of jurisdiction.\nNote\n:  For the purpose of this section, a minor is an individual that has not yet reached the age of majority as set forth in\nM21-1, Part X, Subpart ii, 6.E.3.c\n.",
  "title": "M21-1, Part X, Subpart ii, Chapter 6, Section E - Authorizing Awards for Fiduciary Cases",
  "citation": "Part X, Subpart ii, Chapter 6, Section E",
  "source_url": "https://www.knowva.ebenefits.va.gov/system/templates/selfservice/va_ssnew/help/customer/locale/en-US/portal/554400000001018/content/554400000177978/M21-1-Part-X-Subpart-ii-Chapter-6-Section-E-Authorizing-Awards-for-Fiduciary-Cases",
  "updated": "",
  "scraped_at": "2025-06-16T23:14:53.568203",
  "tags": [
    "m21-1"
  ]
}