{
  "chunk_id": "XI_iii_1_C_15",
  "content": "/>\nXI.iii.1.C.2.c\n.\nEscheat\nVBA will not pay burial benefits if the payment would escheat (that is, would be turned over to the State because there are no heirs to the estate of the person to whom such benefits would be paid).\nIn the absence of a statement from any public or private source that the burial allowance will escheat (be turned over to the State), make no inquiry as to the possibility of escheat.\nReference\n:  For more information on escheat, see\n38 CFR 3.1710\n.",
  "title": "M21-1, Part XI, Subpart iii, Chapter 1, Section C  - Burial Authorization Payment Issues",
  "citation": "Part XI, Subpart iii, Chapter 1, Section C",
  "source_url": "https://www.knowva.ebenefits.va.gov/system/templates/selfservice/va_ssnew/help/customer/locale/en-US/portal/554400000001018/content/554400000174202/M21-1-Part-XI-Subpart-iii-Chapter-1-Section-C-Burial-Authorization-Payment-Issues",
  "updated": "",
  "scraped_at": "2025-06-16T23:21:42.333653",
  "tags": [
    "m21-1"
  ]
}