{
  "chunk_id": "XII_i_4_C_14",
  "content": "/>\nIntroduction\nThis topic contains information on a surviving spouse’s benefit and potential\noffset, including\nVA and RPC policies concerning payment of DIC and SBP\nreplying to RPC inquiries regarding SBP\nactions taken at the time of the RPC inquiry\ncoordinating the payment of DIC with DFAS\ntemplate for requesting information from DFAS\nurgent PTIVA requests\nsending sensitive documents through DFAS\n, and\ncoordinating the payment of DIC with the Coast Guard\n.",
  "title": "M21-1, Part XII, Subpart i, Chapter 4, Section C - Survivor Benefit Plan (SBP) Offsets",
  "citation": "Part XII, Subpart i, Chapter 4, Section C",
  "source_url": "https://www.knowva.ebenefits.va.gov/system/templates/selfservice/va_ssnew/help/customer/locale/en-US/portal/554400000001018/content/554400000175221/M21-1-Part-XII-Subpart-i-Chapter-4-Section-C-Survivor-Benefit-Plan-SBP-Offsets",
  "updated": "",
  "scraped_at": "2025-06-16T23:24:01.271746",
  "tags": [
    "m21-1"
  ]
}