{
  "chunk_id": "XIV_none_4_B_24",
  "content": "/>\nXIV.4.B.2.\nb\n.\nPMC FTI Storage\nPMCs must maintain all FTI created for upfront verification or Post Award Audits (PAA) in the restricted FTI File Repository (FFR).  IVMs may be stored in orange light-weight folders or in the FFR.\nNote\n:  FTI related to IVMs or to upfront verification and PAAs can be viewed via the restricted FTI DOCUMENTS tab within the Veterans Benefits Management System (VBMS).",
  "title": "M21-1, Part XIV, Chapter 4, Section B - Federal Tax Information (FTI) Match: Safeguarding",
  "citation": "Part XIV, Chapter 4, Section B",
  "source_url": "https://www.knowva.ebenefits.va.gov/system/templates/selfservice/va_ssnew/help/customer/locale/en-US/portal/554400000001018/content/554400000173312/M21-1-Part-XIV-Chapter-4-Section-B-Federal-Tax-Information-FTI-Match-Safeguarding",
  "updated": "",
  "scraped_at": "2025-06-16T23:32:22.064620",
  "tags": [
    "m21-1"
  ]
}