{
  "chunk_id": "XIV_none_4_B_42",
  "content": "/>\nXIV.4.B.3.\ne\n.\nReleasing Non-FTI to a Member of Congress\nInformation which is not FTI, including income information provided to VA by an income payer including copies of\nIRS Forms\nW-2\nor\n1040, U.S. Individual Income Tax Return\n, filed with the IRS, may be released to a Member of Congress only when the Member of Congress seeks the\ninformation at the request of the beneficiary or someone authorized to exercise the beneficiary’s access right under these statutes, or\nrecords on behalf of a Congressional committee with VA oversight jurisdiction for committee business.",
  "title": "M21-1, Part XIV, Chapter 4, Section B - Federal Tax Information (FTI) Match: Safeguarding",
  "citation": "Part XIV, Chapter 4, Section B",
  "source_url": "https://www.knowva.ebenefits.va.gov/system/templates/selfservice/va_ssnew/help/customer/locale/en-US/portal/554400000001018/content/554400000173312/M21-1-Part-XIV-Chapter-4-Section-B-Federal-Tax-Information-FTI-Match-Safeguarding",
  "updated": "",
  "scraped_at": "2025-06-16T23:32:22.064620",
  "tags": [
    "m21-1"
  ]
}