{
  "chunk_id": "XIV_none_4_B_53",
  "content": "/>\nXIV.4.B.4.f\n.\nNotifying Federal Fiduciaries of Award Changes\nAward letters containing rate changes may be sent to a Federal fiduciary only if FTI is not contained within the letter.  If FTI is contained within the letter, send a separate letter notifying the fiduciary of award changes using the following language:\nWe are contacting you because we have adjusted\n[insert beneficiary’s name]\naward due to federal tax information (FTI) that was previously unreported.  We have sent letters directly to\n[insert beneficiary’s name]\nregarding this issue because federal law prohibits us from disclosing FTI to anyone other than the taxpayer unless the fiduciary has been appointed by a court of law.  If you have been appointed fiduciary by a court of law, please provide us evidence of the appointment.\nWe have adjusted\n[\ninsert beneficiary’s name\n]\npayments as follows:\n[\nInsert rate and effective date table from beneficiary’s letter\n.]",
  "title": "M21-1, Part XIV, Chapter 4, Section B - Federal Tax Information (FTI) Match: Safeguarding",
  "citation": "Part XIV, Chapter 4, Section B",
  "source_url": "https://www.knowva.ebenefits.va.gov/system/templates/selfservice/va_ssnew/help/customer/locale/en-US/portal/554400000001018/content/554400000173312/M21-1-Part-XIV-Chapter-4-Section-B-Federal-Tax-Information-FTI-Match-Safeguarding",
  "updated": "",
  "scraped_at": "2025-06-16T23:32:22.064620",
  "tags": [
    "m21-1"
  ]
}